beeb/__init__.py
beeb/api/__init__.py
beeb/api/api_helpers.py
beeb/api/html_helpers.py
beeb/api/json_helpers.py
beeb/api/serialisation.py
beeb/api/url_helpers.py
beeb/api/xml_helpers.py
beeb/data/__init__.py
beeb/data/store/__init__.py
beeb/data/store/programme_catalogue.db
beeb/nav/__init__.py
beeb/nav/channel_ids.py
beeb/nav/cat/__init__.py
beeb/nav/cat/catalogue.py
beeb/nav/cat/guide.py
beeb/nav/sched/__init__.py
beeb/nav/sched/async_utils.py
beeb/nav/sched/broadcasts.py
beeb/nav/sched/listings.py
beeb/nav/sched/programme.py
beeb/nav/sched/remote.py
beeb/nav/sched/schedule.py
beeb/nav/search/__init__.py
beeb/nav/search/search_cat.py
beeb/nav/search/search_sched.py
beeb/nav/search/sieve.py
beeb/share/__init__.py
beeb/share/db_utils.py
beeb/share/http_utils.py
beeb/share/multiproc_utils.py
beeb/share/time/__init__.py
beeb/share/time/cal_utils.py
beeb/share/time/isotime.py
beeb/stream/__init__.py
beeb/stream/async_utils.py
beeb/stream/episode.py
beeb/stream/preproc.py
beeb/stream/station.py
beeb/stream/streams.py
beeb/stream/urlsets.py
beeb-2.4.2.dist-info/LICENSE
beeb-2.4.2.dist-info/METADATA
beeb-2.4.2.dist-info/WHEEL
beeb-2.4.2.dist-info/top_level.txt
beeb-2.4.2.dist-info/RECORD
