Metadata-Version: 2.1
Name: beeb
Version: 2.4.2
Summary: A modern interface to the BBC Sounds radio catalogue
Home-page: https://github.com/lmmx/beeb
Author: Louis Maddox
Author-email: louismmx@gmail.com
License: MIT License
Platform: UNKNOWN
Classifier: Programming Language :: Python :: 3
Classifier: Operating System :: OS Independent
Classifier: License :: OSI Approved :: MIT License
Classifier: Topic :: Multimedia :: Sound/Audio
Requires-Python: >=3
Requires-Dist: bs4
Requires-Dist: ffmpeg-python
Requires-Dist: httpx[http2]
Requires-Dist: aiostream
Requires-Dist: aiofiles
Requires-Dist: tqdm
Requires-Dist: more-itertools
Requires-Dist: python-dateutil
